staticjinja/__init__.py
staticjinja/__main__.py
staticjinja/cli.py
staticjinja/reloader.py
staticjinja/staticjinja.py
staticjinja2-0.4.0b1.dist-info/DESCRIPTION.rst
staticjinja2-0.4.0b1.dist-info/METADATA
staticjinja2-0.4.0b1.dist-info/RECORD
staticjinja2-0.4.0b1.dist-info/WHEEL
staticjinja2-0.4.0b1.dist-info/entry_points.txt
staticjinja2-0.4.0b1.dist-info/metadata.json
staticjinja2-0.4.0b1.dist-info/top_level.txt
