Metadata-Version: 2.0
Name: staticjinja2
Version: 0.4.0b1
Summary: Original Author: Ceasar Bautista - jinja based static site generator
Home-page: https://github.com/lstn/staticjinja
Author: Lucas Estienne
Author-email: lucas@limaecho.ca
License: UNKNOWN
Keywords: staticjinja,jinja,static,website
Platform: UNKNOWN
Classifier: Intended Audience :: Developers
Classifier: License :: OSI Approved :: MIT License
Classifier: Operating System :: OS Independent
Classifier: Programming Language :: Python
Classifier: Programming Language :: Python :: 2
Classifier: Programming Language :: Python :: 2.6
Classifier: Programming Language :: Python :: 2.7
Classifier: Programming Language :: Python :: 3
Classifier: Programming Language :: Python :: 3.3
Classifier: Programming Language :: Python :: 3.4
Classifier: Programming Language :: Python :: 3.5
Classifier: Programming Language :: Python :: 3.6
Classifier: Topic :: Software Development :: Libraries :: Python Modules
Classifier: Development Status :: 4 - Beta
Requires-Dist: PyYAML
Requires-Dist: docopt
Requires-Dist: easywatch
Requires-Dist: jinja2
